beancount_tx_cleanup/__init__.py
beancount_tx_cleanup/cleaner.py
beancount_tx_cleanup/helpers.py
beancount_tx_cleanup/utils.py
beancount_tx_cleanup-0.1.1.dist-info/WHEEL
beancount_tx_cleanup-0.1.1.dist-info/METADATA
beancount_tx_cleanup-0.1.1.dist-info/RECORD
