Metadata-Version: 2.3
Name: beancount-tx-cleanup
Version: 0.1.1
Summary: Beancount transaction cleaner
Author: Jakub Turski
Author-email: Jakub Turski <yacoob@ftml.net>
Requires-Dist: beancount~=2.3
Requires-Dist: pydantic~=2.8
Requires-Python: >=3.11
Project-URL: Repository, https://github.com/yacoob/beancount-tx-cleanup
